{"ankama_id": 274, "categorie": "resources", "name": "Pièce du Puzzle de la Griffe", "type": "{"name": "Pierre brute", "id": 91}", "level": 43, "image_urls": {"icon": "https://api.dofusdu.de/dofus2/img/item/51267.png", "sd": "https://api.dofusdu.de/dofus2/img/item/51267-200.png", "hq": "https://api.dofusdu.de/dofus2/img/item/51267-400.png", "hd": "https://api.dofusdu.de/dofus2/img/item/51267-800.png"}, "description": "Une pièce très rare du trésor de Dodge, l"un des plus grands Ecaflip d"Amakna.", "effects": none, "recipe": none, "conditions": none, "is_weapon": none, "pods": none, "parent_set": none, "critical_hit_probability": none, "critical_hit_bonus": none, "is_two_handed": none, "max_cast_per_turn": none, "ap_cost": none, "range": none, "condition_tree": none}